tfshow/__init__.py
tfshow/main.py
tfshow/tfreader.py
tfshow/tfshow.py
tfshow-0.0.1.dist-info/LICENSE
tfshow-0.0.1.dist-info/METADATA
tfshow-0.0.1.dist-info/WHEEL
tfshow-0.0.1.dist-info/entry_points.txt
tfshow-0.0.1.dist-info/top_level.txt
tfshow-0.0.1.dist-info/RECORD
