Metadata-Version: 2.1
Name: tfshow
Version: 0.0.1
Summary: Cyber tf visualizer
Home-page: https://github.com/daohu527/tfshow
Author: daohu527
Author-email: daohu527@gmail.com
License: UNKNOWN
Project-URL: Bug Tracker, https://github.com/daohu527/tfshow/issues
Platform: UNKNOWN
Classifier: Programming Language :: Python :: 3
Classifier: License :: OSI Approved :: Apache Software License
Classifier: Operating System :: OS Independent
Requires-Python: >=3.6
Requires-Dist: graphviz
Requires-Dist: cyber-record
